django_template_block_args
example_project
