Metadata-Version: 2.1
Name: django-template-block-args
Version: 0.0.5
Summary: UNKNOWN
Home-page: https://github.com/AlexCLeduc/django-template-block-arg
Author: AlexCLeduc
License: UNKNOWN
Platform: UNKNOWN
Classifier: Programming Language :: Python :: 3
Classifier: License :: OSI Approved :: MIT License
Classifier: Operating System :: OS Independent
